surquest/utils/loader/__init__.py
surquest/utils/loader/loader.py
surquest_utils_loader-0.0.1.dist-info/METADATA
surquest_utils_loader-0.0.1.dist-info/WHEEL
surquest_utils_loader-0.0.1.dist-info/licenses/LICENSE
surquest_utils_loader-0.0.1.dist-info/RECORD
