Metadata-Version: 2.1
Name: surquest-utils-loader
Version: 0.0.1
Summary: Standalone Loader class for simplification of loading configurations from YAML, JSON, SQL or TXT files.
Project-URL: Homepage, https://github.com/surquest/python-utils-loader
Project-URL: Bug Tracker, https://github.com/surquest/python-utils-loader/issues
Author-email: Michal Švarc <michal.svarc@surquest.com>
License-File: LICENSE
Requires-Dist: pyyaml>=6.0
Provides-Extra: test
Requires-Dist: pytest-cov==4.0.0; extra == 'test'
Requires-Dist: pytest==7.2.1; extra == 'test'
